a2apay/__init__.py
a2apay/agent.py
a2apay/protocol.py
a2apay/resource.py
a2apay/transaction.py
a2apay/wallet.py
a2apay-1.0.0.dist-info/licenses/LICENSE
a2apay-1.0.0.dist-info/METADATA
a2apay-1.0.0.dist-info/WHEEL
a2apay-1.0.0.dist-info/top_level.txt
a2apay-1.0.0.dist-info/RECORD
