Metadata-Version: 2.4
Name: a2apay
Version: 1.0.0
Summary: Secure, modular microtransaction framework for agent-to-agent (A2A) and agent-to-resource (MCP) payments.
Home-page: https://github.com/DwirefS/a2a_payments_framework
Author: Dwiref Sharma
Author-email: dwirefz@hotmail.com
Classifier: Development Status :: 4 - Beta
Classifier: Intended Audience :: Developers
Classifier: Topic :: Software Development :: Libraries
Classifier: License :: OSI Approved :: MIT License
Classifier: Programming Language :: Python :: 3
Classifier: Programming Language :: Python :: 3.8
Classifier: Programming Language :: Python :: 3.9
Classifier: Programming Language :: Python :: 3.10
Requires-Python: >=3.8
License-File: LICENSE
Requires-Dist: pytest
Requires-Dist: flake8
Dynamic: author
Dynamic: author-email
Dynamic: classifier
Dynamic: description
Dynamic: description-content-type
Dynamic: home-page
Dynamic: license-file
Dynamic: requires-dist
Dynamic: requires-python
Dynamic: summary
